setup.py
gaebusiness/__init__.py
gaebusiness/business.py
gaebusiness/gaeutil.py
gaebusiness.egg-info/PKG-INFO
gaebusiness.egg-info/SOURCES.txt
gaebusiness.egg-info/dependency_links.txt
gaebusiness.egg-info/not-zip-safe
gaebusiness.egg-info/requires.txt
gaebusiness.egg-info/top_level.txt